Pypsy/__init__.py
Pypsy/optimization/__init__.py
Pypsy/signal/__init__.py
Pypsy/signal/analysis.py
Pypsy/signal/conversion.py
Pypsy/signal/filter.py
Pypsy/signal/utilities.py
Pypsy/tests/__init__.py
Pypsy-0.1.5.dist-info/DESCRIPTION.rst
Pypsy-0.1.5.dist-info/METADATA
Pypsy-0.1.5.dist-info/RECORD
Pypsy-0.1.5.dist-info/WHEEL
Pypsy-0.1.5.dist-info/metadata.json
Pypsy-0.1.5.dist-info/top_level.txt
