Metadata-Version: 2.0
Name: Pypsy
Version: 0.1.5
Summary: Electrodermal activity processing and analysis
Home-page: http://www.musicsensorsemotion.com
Author: Brennon Bortz
Author-email: brennon@vt.edu
License: MIT
Platform: UNKNOWN
Requires-Dist: numpy
Requires-Dist: scipy
Requires-Dist: sklearn
